autocommand/__init__.py
autocommand/autoasync.py
autocommand/autocommand.py
autocommand/automain.py
autocommand/autoparse.py
autocommand/errors.py
autocommand-2.2.1.dist-info/DESCRIPTION.rst
autocommand-2.2.1.dist-info/METADATA
autocommand-2.2.1.dist-info/RECORD
autocommand-2.2.1.dist-info/WHEEL
autocommand-2.2.1.dist-info/metadata.json
autocommand-2.2.1.dist-info/top_level.txt
